{"01-0":{"main":"29ec457cef"},"02-0":{"main":"34fa45796086"},"03-0":{"main":"337c956167b14a0e"},"04-0":{"main":"327c9f72e564"},"05-0":{"main":"2bf05b7be5"},"06-0":{"main":"2af04270f6"},"07-0":{"main":"33f04460ea"},"08-0":{"main":"34fa42f1147a"},"09-0":{"main":"3a7c9578f673"},"10-0":{"main":"367bb971e179"},"11-0":{"main":"a40fccabe873c2"},"12-0":{"main":"2c7bb978e578"},"13-0":{"main":"a521cd85f6f239dc"},"14-0":{"main":"21f4427af6"},"15-0":{"main":"33fa4df11464"},"16-0":{"main":"a40f5df11478c8"},"17-0":{"main":"25f35370e9"},"18-0":{"main":"2df0457afe"},"19-0":{"main":"21fdcd85e073"},"20-0":{"main":"33f6cdabed64"},"21-0":{"main":"34f05974e8"},"22-0":{"main":"2bfe477cf0"},"23-0":{"main":"25f14ef11478"},"24-0":{"main":"a338467e67b1c8"},"25-0":{"main":"217b9779e57d"},"26-0":{"main":"2bf05060ea"},"27-0":{"main":"34f04274f0"},"28-0":{"main":"23f0ccabe977"},"29-0":{"main":"30f34861eb"},"30-0":{"main":"247bb9f13a73db"},"month":6,"year":2022}