{
    "year": 2022,
    "month": 6,
    "01-0": {
        "main": "ÇANAK"
    },
    "02-0": {
        "main": "KABAK"
    },
    "03-0": {
        "main": "TARAK"
    },
    "04-0": {
        "main": "TABAK"
    },
    "05-0": {
        "main": "TÜFEK"
    },
    "06-0": {
        "main": "OTLAK"
    },
    "07-0": {
        "main": "YAĞIŞ"
    },
    "08-0": {
        "main": "YAPAY"
    },
    "09-0": {
        "main": "TANIK"
    },
    "10-0": {
        "main": "BİLİM"
    },
    "11-0": {
        "main": "NESİL"
    },
    "12-0": {
        "main": "DEYİM"
    },
    "13-0": {
        "main": "EMZİK"
    },
    "14-0": {
        "main": "ZARİF"
    },
    "15-0": {
        "main": "ÖZGÜN"
    },
    "16-0": {
        "main": "CAHİL"
    },
    "17-0": {
        "main": "JOKER"
    },
    "18-0": {
        "main": "PEMBE"
    },
    "19-0": {
        "main": "FATİH"
    },
    "20-0": {
        "main": "TEZEK"
    },
    "21-0": {
        "main": "GOLCÜ"
    },
    "22-0": {
        "main": "HAZİN"
    },
    "23-0": {
        "main": "MADDİ"
    },
    "24-0": {
        "main": "BULUT"
    },
    "25-0": {
        "main": "İSKAN"
    },
    "26-0": {
        "main": "EMSAL"
    },
    "27-0": {
        "main": "MAKUL"
    },
    "28-0": {
        "main": "ÜÇGEN"
    },
    "29-0": {
        "main": "VERGİ"
    },
    "30-0": {
        "main": "BULUŞ"
    }
}